<?xml version="1.0" encoding="ISO-8859-1"?>
<eml:eml xmlns:eml="eml://ecoinformatics.org/eml-2.1.1" xmlns:dc="http://purl.org/dc/terms/" xmlns:xsi="http://www.w3.org/2001/XMLSchema-instance" xsi:schemaLocation="eml://ecoinformatics.org/eml-2.1.1 http://rs.gbif.org/schema/eml-gbif-profile/1.0.1/eml.xsd" packageId="de558156-c78a-4b01-bef8-d87d0ed88929" system="https://symbiota.org" scope="system" xml:lang="eng"><dataset><title xml:lang="eng">SEINet Portal Network general data extract</title><creator id="4342b7ac-e565-4ed1-8ff8-ae4769d9ef15"><organizationName>SEINet Portal Network</organizationName><electronicMailAddress>seinetadmin@asu.edu</electronicMailAddress><onlineUrl>https://swbiodiversity.org/seinet/index.php</onlineUrl></creator><metadataProvider><organizationName>SEINet Portal Network</organizationName><electronicMailAddress>seinetadmin@asu.edu</electronicMailAddress><onlineUrl>https://swbiodiversity.org/seinet/index.php</onlineUrl></metadataProvider><pubDate>2021-07-19</pubDate><language>eng</language></dataset><additionalMetadata><metadata><symbiota><dateStamp>2021-07-19T13:46:40-07:00</dateStamp><citation identifier="50ddeb3b-c29d-430d-9f71-8aab6f62bd2a">SEINet Portal Network - 50ddeb3b-c29d-430d-9f71-8aab6f62bd2a</citation><physical><characterEncoding>ISO-8859-1</characterEncoding><dataFormat><externallyDefinedFormat><formatName>Darwin Core Archive</formatName></externallyDefinedFormat></dataFormat></physical><collection identifier="ca77be98-2a59-4aa9-bfc1-5ea615f2e6b7" id="113"><alternateIdentifier>https://swbiodiversity.org/seinet/collections/misc/collprofiles.php?collid=113</alternateIdentifier><parentCollectionIdentifier>DBG</parentCollectionIdentifier><collectionIdentifier>KHD</collectionIdentifier><collectionName>Kathryn Kalmbach Herbarium</collectionName><resourceLogoUrl>https://swbiodiversity.org/seinet/content/collicon/dbg.jpg</resourceLogoUrl><onlineUrl>http://www.botanicgardens.org/science-research/our-collections</onlineUrl><intellectualRights>http://creativecommons.org/publicdomain/zero/1.0/</intellectualRights><additionalInfo>Public Domain</additionalInfo><associatedParty><individualName><surName>Rick Levy, Database Associate</surName><givenName></givenName></individualName><electronicMailAddress>richard.levy@botanicgardens.org</electronicMailAddress></associatedParty><abstract><para>The Kathryn Kalmbach Herbarium (KHD), a collection of over 67,000 vascular plant specimens, is a regional herbarium with a research focus on the species diversity of Colorado and the Southern Rocky Mountain region. The collection also contains species that are in cultivation at Denver Botanic Gardens. Most of the specimens within the collection have been digitized, and their photographs may be found online. Higher resolution images are also available upon request. Specimens collected in 2017 and later are likely to have an associated tissue sample available on GGBN.</para></abstract></collection><collection identifier="a13355a1-1ccc-46d9-9672-521d8d668804" id="147"><alternateIdentifier>https://swbiodiversity.org/seinet/collections/misc/collprofiles.php?collid=147</alternateIdentifier><parentCollectionIdentifier>USCH</parentCollectionIdentifier><collectionIdentifier></collectionIdentifier><collectionName>University of South Carolina, A. C. Moore Herbarium</collectionName><resourceLogoUrl>https://sernecportal.org/portal/content/collicon/usch.jpg</resourceLogoUrl><onlineUrl>http://www.herbarium.org</onlineUrl><intellectualRights>http://creativecommons.org/licenses/by-nc/3.0/</intellectualRights><associatedParty><individualName><surName>Dr. Herrick Brown, Curator</surName><givenName></givenName></individualName><electronicMailAddress>hbrown@mailbox.sc.edu</electronicMailAddress></associatedParty><abstract><para>The A. C. Moore Herbarium is an important part of the Department of Biological Sciences at the University of South Carolina (Columbia Campus). Founded in 1907 by Dr. Andrew Charles Moore, the original collection of dried plant specimens is now part of an ever-growing collection. Total holdings are just over 120,000 specimens, making the A. C. Moore Herbarium the largest in the state of South Carolina. Researchers and visitors will find a diverse collection of vascular and nonvascular plant material primarily from the Southeastern United States and more specifically from South Carolina. Now over 100 years old, the A. C. Moore Herbarium continues to be an indispensable resource for botanical knowledge.</para></abstract></collection><collection identifier="8219517e-d317-49d2-9c1f-b44df96d6cec" id="181"><alternateIdentifier>https://swbiodiversity.org/seinet/collections/misc/collprofiles.php?collid=181</alternateIdentifier><parentCollectionIdentifier>F</parentCollectionIdentifier><collectionIdentifier>Botany</collectionIdentifier><collectionName>Field Museum of Natural History</collectionName><resourceLogoUrl>https://sernecportal.org/portal/content/collicon/f.jpg</resourceLogoUrl><onlineUrl>http://fieldmuseum.org/explore/department/botany/collections</onlineUrl><intellectualRights>http://creativecommons.org/licenses/by-nc/3.0/</intellectualRights><associatedParty><individualName><surName>Christine Niezgoda</surName><givenName></givenName></individualName><electronicMailAddress>cniezgoda@fieldmuseum.org</electronicMailAddress></associatedParty><abstract><para>Phanerogams worldwide with emphasis on tropical and North America, especially rich in collections from Mexico, Guatemala, Costa Rica, Colombia, Venezuela, Ecuador, and Peru; pteridophytes worldwide with emphasis on Guatemala, Costa Rica, Ecuador, and Peru; bryophytes worldwide; mosses of North America, Central America, Andean South America, and Australasia; hepatics of north temperate, South America, and south temperate; all groups of fungi, especially basidiomycetes with emphasis on New World and lichenized fungi of north temperate and Central America; algae worldwide, especially Cyanobacteria; economic botany.</para></abstract></collection><collection identifier="b18db63b-13de-4aa8-b16a-615f312e66df" id="223"><alternateIdentifier>https://swbiodiversity.org/seinet/collections/misc/collprofiles.php?collid=223</alternateIdentifier><parentCollectionIdentifier>SRSC</parentCollectionIdentifier><collectionIdentifier></collectionIdentifier><collectionName>Sul Ross University A. Michael Powell Herbarium</collectionName><resourceLogoUrl>https://sernecportal.org/portal/content/collicon/srsc.jpg</resourceLogoUrl><onlineUrl>http://www.sulross.edu/page/1009/biology-collections</onlineUrl><intellectualRights>http://creativecommons.org/licenses/by-nc/3.0/</intellectualRights><additionalInfo>Sul Ross University</additionalInfo><associatedParty><individualName><surName>A. Michael Powell</surName><givenName></givenName></individualName><electronicMailAddress>ampowell@sulross.edu</electronicMailAddress></associatedParty><abstract><para>The herbarium occupies one wing of the Warnock Science Building. There are approximately 100,000 specimens housed in 112 cases. The major collections include plants of Trans-Pecos Texas, which forms the largest part of the northern part of the Chihuahuan Desert Region in the United States. It is a prominent regional research collection that is available to botanists around the world and is also a valuable teaching facility for both graduate and undergraduate students interested in various botanical disciplines or in wildlife biology. The first significant collections are those made by O.E. Sperry in 1935-1946. The physical herbarium was probably started by L.C. Hinkley but B.H. Warnock was responsible for the largest early collection of plants and major development of the herbarium as a research facility. Another major contributor was M.C Johnston. More recently, the herbarium has grown through the efforts of A.M. Powell, in whose honor the university renamed the herbarium in 2003.</para></abstract></collection><collection identifier="024f44f2-a2f5-4daa-b306-c11efb5aa4d0" id="254"><alternateIdentifier>https://swbiodiversity.org/seinet/collections/misc/collprofiles.php?collid=254</alternateIdentifier><parentCollectionIdentifier>NCSC</parentCollectionIdentifier><collectionIdentifier></collectionIdentifier><collectionName>North Carolina State University Vascular Plant Herbarium</collectionName><resourceLogoUrl>https://swbiodiversity.org/seinet/content/collicon/ncsc.png</resourceLogoUrl><onlineUrl>http://herbarium.ncsu.edu</onlineUrl><intellectualRights>http://creativecommons.org/licenses/by-nc/3.0/</intellectualRights><abstract></abstract><associatedParty><individualName><surName>Alexander Krings</surName><givenName></givenName></individualName><electronicMailAddress>akrings@ncsu.edu</electronicMailAddress></associatedParty></collection><collection identifier="c75cb98d-a881-45ce-a4f7-e4f28ef32afe" id="366"><alternateIdentifier>https://swbiodiversity.org/seinet/collections/misc/collprofiles.php?collid=366</alternateIdentifier><parentCollectionIdentifier>TEX</parentCollectionIdentifier><collectionIdentifier></collectionIdentifier><collectionName>University of Texas at Austin Herbarium</collectionName><resourceLogoUrl>https://swbiodiversity.org/seinet/content/collicon/tex.jpg</resourceLogoUrl><onlineUrl>https://biodiversity.utexas.edu/resources/collections/plants</onlineUrl><intellectualRights>http://creativecommons.org/publicdomain/zero/1.0/</intellectualRights><associatedParty><individualName><surName>George Yatskievych</surName><givenName></givenName></individualName><electronicMailAddress>george.yatskievych@austin.utexas.edu</electronicMailAddress></associatedParty><abstract><para>The University of Texas Herbarium (TEX) is part of the Billie L. Turner Plant Resources Center, which houses the combined herbaria of TEX and the Lundell Herbarium (LL). The combined PRC collections include over one million specimens from all parts of the world and represent the 13th largest herbarium in the United States. The two herbaria (TEX and LL) are completely integrated and interfiled, although each sheet is marked as to its herbarium and should be cited as such. The University of Texas Herbarium itself, with close to 700,000 specimens, dates to about 1890 and is especially strong in Texas and Mexican specimens. The research interests of faculty, staff, and graduate students have led to very strong representation of Asteraceae, Fabaceae, and Rhamnaceae, among other families, as well as the Chihuahuan Desert region (Mexico and the U.S.) and the mountains and plains of northeastern Mexico. All new specimens received into the Plant Resources Center are now accessioned into TEX.</para></abstract></collection><collection identifier="f5da8b4f-e389-4436-b71d-1c3e0a4baacc" id="368"><alternateIdentifier>https://swbiodiversity.org/seinet/collections/misc/collprofiles.php?collid=368</alternateIdentifier><parentCollectionIdentifier>COLO</parentCollectionIdentifier><collectionIdentifier>V</collectionIdentifier><collectionName>University of Colorado Museum of Natural History Herbarium Vascular Plant Collection</collectionName><resourceLogoUrl>https://botanydb.colorado.edu/COLO_Botany.jpg</resourceLogoUrl><onlineUrl>https://botanydb.colorado.edu</onlineUrl><intellectualRights>http://creativecommons.org/licenses/by-nc/3.0/</intellectualRights><associatedParty><individualName><surName>Allen</surName><givenName>J Ryan</givenName></individualName><electronicMailAddress>james.r.allen@colorado.edu</electronicMailAddress><positionName>Biodiversity Informatics Manager</positionName><userId>https://orcid.org/0000-0002-4240-0809</userId></associatedParty><associatedParty><individualName><surName>Clark</surName><givenName>Dina</givenName></individualName><positionName>Collection Manager</positionName><electronicMailAddress>dina.clark@colorado.edu</electronicMailAddress></associatedParty><abstract><para>&lt;B&gt;This database represents a snapshot of our primary database housed at https://botanydb.colorado.edu and may not be as up to date as our primary database.&lt;/b&gt;&lt;br/&gt;&lt;br/&gt;&lt;b&gt;Collection strengths:&lt;/b&gt; Colorado, Southern Rocky Mountains and Western North American vascular plants and cryptogams, worldwide arctic and alpine, Appalachia, Galapagos Lichens, Australia, New Guinea, Altai, Mexico and the Seville Flowers Bryophyte Collection. &lt;br/&gt;&lt;br/&gt; &lt;b&gt;Digitization:&lt;/b&gt; Digitization efforts have been focused on North American vascular plants, lichens and bryophytes with an emphasis on Colorado specimens. All Colorado vascular and cryptogam specimens have been imaged and entered into the database. Images for North American vascular plants are captured for 18 families under the Tri-Trophic TCN. North American lichen packets have been imaged and transcribed http://lichenportal.org/portal. All North American bryophyte packets have been imaged and all Colorado specimens have been transcribed and are available at http://bryophyteportal.org/portal. 140,000 vascular plant specimens and 55,000 bryophytes and 47,000 lichens from outside of North America have not been digitized.</para></abstract></collection><collection identifier="fea81a47-2365-45cc-bef9-b6bbff7457e6" id="370"><alternateIdentifier>https://swbiodiversity.org/seinet/collections/misc/collprofiles.php?collid=370</alternateIdentifier><parentCollectionIdentifier>BRIT</parentCollectionIdentifier><collectionIdentifier></collectionIdentifier><collectionName>Botanical Research Institute of Texas, Philecology Herbarium</collectionName><resourceLogoUrl>https://portal.torcherbaria.org/portal/content/collicon/brit.png</resourceLogoUrl><onlineUrl>http://www.brit.org</onlineUrl><intellectualRights>http://creativecommons.org/licenses/by/4.0/</intellectualRights><additionalInfo>Botanical Research Institute of Texas</additionalInfo><abstract></abstract><associatedParty><individualName><surName>Tiana Rehman</surName><givenName></givenName></individualName><electronicMailAddress>trehman@brit.org</electronicMailAddress></associatedParty></collection><collection identifier="urn:lsid:biocol.org:col:15631" id="462"><alternateIdentifier>https://swbiodiversity.org/seinet/collections/misc/collprofiles.php?collid=462</alternateIdentifier><parentCollectionIdentifier>Harvard</parentCollectionIdentifier><collectionIdentifier></collectionIdentifier><collectionName>Harvard University Herbaria: Vascular Plants of North America</collectionName><resourceLogoUrl>https://bryophyteportal.org/portal/content/collicon/fh.png</resourceLogoUrl><onlineUrl>https://huh.harvard.edu/</onlineUrl><intellectualRights>http://creativecommons.org/licenses/by-nc/3.0/</intellectualRights><associatedParty><individualName><surName>Jonathan Kennedy</surName><givenName></givenName></individualName><electronicMailAddress>jonathan_kennedy@harvard.edu</electronicMailAddress></associatedParty><abstract><para>The Harvard University Herbaria, with over 5 million specimens, is the world&#8217;s largest University Herbaria. Included in the Herbaria are what were once six separate herbarium collections: * Herbarium of the Arnold Arboretum (A) * Economic Herbarium of Oakes Ames (ECON) * Oakes Ames Orchid Herbarium (AMES) * Farlow Herbarium (FH) * Gray Herbarium (GH) * New England Botanical Club Herbarium (NEBC).</para></abstract></collection><collection identifier="1b1022c0-6a5b-4791-8beb-bf9d7c63fd89" id="474"><alternateIdentifier>https://swbiodiversity.org/seinet/collections/misc/collprofiles.php?collid=474</alternateIdentifier><parentCollectionIdentifier>SAT</parentCollectionIdentifier><collectionIdentifier></collectionIdentifier><collectionName>Angelo State University Herbarium</collectionName><resourceLogoUrl>https://portal.torcherbaria.org/portal/content/collicon/sat.png</resourceLogoUrl><onlineUrl>https://www.angelo.edu/content/profiles/5160-herbarium/Templates/profiles-asnhc</onlineUrl><intellectualRights>http://creativecommons.org/licenses/by-nc/4.0/</intellectualRights><associatedParty><individualName><surName>Amos</surName><givenName>Bonnie</givenName></individualName><electronicMailAddress>bonnie.amos@angelo.edu</electronicMailAddress><positionName>Curator</positionName></associatedParty><associatedParty><individualName><surName>Brady</surName><givenName>Serina</givenName></individualName><positionName>Collection Manager</positionName><electronicMailAddress>serina.brady@angelo.edu</electronicMailAddress></associatedParty><abstract><para>The ASU Herbarium is the largest component of the Angelo State Natural History Collections (ASNHC) and comprises about 80,000 plant specimens, with significant holdings in the Poaceae and Cyperaceae families. It is the eighth-largest herbarium in Texas, and represents the most complete floristic inventory of the Concho Valley region. In addition, the Herbarium serves as a permanent depository for voucher specimens for floristic surveys of several unique areas in West Texas, including Big Bend National Park, Texas Nature Conservancy Big Brushy Canyon, and Texas Nature Conservancy Independence Creek. Specimens from several ecological and systematic studies of rare plants are also housed in our collection. Glenn Casey started the Herbarium in the 1940s. At that time, it was called the Goodman Herbarium, in honor of the late Oklahoma botanist, Dr. George Goodman. The collection languished briefly in the late 1960s after Casey&#8217;s departure and during ASU&#8217;s transition from the two-year San Angelo College to Angelo State University. It was revitalized in 1972 with the arrival of Dr. Chester Rowell Jr., who served as curator until his retirement in 1987. At that time, Dr. Bonnie Amos became curator, and she remains in that position to this day. The ASU Herbarium invites review of specimen identification--please contact the Collections Manager with any suggested updates to listed taxonomy.</para></abstract></collection></symbiota></metadata></additionalMetadata></eml:eml>
